cfastrank-0.4.0.dist-info/METADATA
cfastrank-0.4.0.dist-info/WHEEL
cfastrank/__init__.py
cfastrank/ffi.py
cfastrank/native.so
cfastrank-0.4.0.dist-info/RECORD
