Metadata-Version: 2.1
Name: cfastrank
Version: 0.4.0
Summary: C API to FastRank Learning to Rank Library written in Rust.
Home-Page: https://github.com/jjfiv/fastrank
Author: John Foley <jjfoley@smith.edu>
Author-Email: John Foley <jjfoley@smith.edu>
License: MIT
